README.md
setup.py
loreio_sdk.egg-info/PKG-INFO
loreio_sdk.egg-info/SOURCES.txt
loreio_sdk.egg-info/dependency_links.txt
loreio_sdk.egg-info/requires.txt
loreio_sdk.egg-info/top_level.txt
loreiosdk/__init__.py
loreiosdk/__main__.py
loreiosdk/spyglass.py
loreiosdk/spyglass_script.py
loreiosdk/utils/__init__.py
loreiosdk/utils/command_argparse.py
samples/__init__.py
samples/automap.py
samples/cdm.py
samples/delete_source.py
samples/download_stream.py
samples/get_streaming_data.py
samples/monitoring.py
samples/ping.py