Metadata-Version: 2.1
Name: loreio-sdk
Version: 0.5.7
Summary: Lore IO sdk
Home-page: UNKNOWN
Author: Maurin Lenglart
Author-email: maurin@loreio.com
License: UNKNOWN
Platform: UNKNOWN
Classifier: License :: OSI Approved :: MIT License
Classifier: Programming Language :: Python :: 2.7
Classifier: Programming Language :: Python :: 3
Classifier: Programming Language :: Python :: 3.7
Classifier: Operating System :: OS Independent
